<?xml version="1.0" encoding="utf-8" ?>
<dwsync>
<file name="html5shiv.js" server="C:/xampp/htdocs/php_test/" local="130249526578730509" remote="130249526570000000" Dst="2" />
<file name="graph.js" server="C:/xampp/htdocs/php_test/" local="130264310741061913" remote="130264310740000000" Dst="2" />
<file name="jquery.flot.js" server="C:/xampp/htdocs/php_test/" local="130263410287489686" remote="130263410280000000" Dst="2" />
<file name="jquery.js" server="C:/xampp/htdocs/php_test/" local="130262509015175840" remote="130262509010000000" Dst="2" />
<file name="jquery.flot.resize.js" server="C:/xampp/htdocs/php_test/" local="130263293570913694" remote="130263293570000000" Dst="2" />
<file name="jquery.flot.crosshair.js" server="C:/xampp/htdocs/php_test/" local="130263210644060641" remote="130263210640000000" Dst="2" />
<file name="jquery.flot.time.js" server="C:/xampp/htdocs/php_test/" local="130263273103675587" remote="130263273100000000" Dst="2" />
<file name="date.js" server="C:/xampp/htdocs/php_test/" local="130263274551898816" remote="130263274550000000" Dst="2" />
<file name="jquery.js" server="D:/documents/Dropbox/School/jaar4/Minor/minorsite/" local="130262509015175840" remote="130262509010000000" Dst="2" />
<file name="jquery.flot.js" server="D:/documents/Dropbox/School/jaar4/Minor/minorsite/" local="130266636306654296" remote="130266636300000000" Dst="2" />
<file name="jquery.flot.crosshair.js" server="D:/documents/Dropbox/School/jaar4/Minor/minorsite/" local="130263210644060641" remote="130263210640000000" Dst="2" />
<file name="jquery.flot.time.js" server="D:/documents/Dropbox/School/jaar4/Minor/minorsite/" local="130263273103675587" remote="130263273100000000" Dst="2" />
<file name="jquery.flot.resize.js" server="D:/documents/Dropbox/School/jaar4/Minor/minorsite/" local="130266994568796965" remote="130266994560000000" Dst="2" />
<file name="graph.js" server="D:/documents/Dropbox/School/jaar4/Minor/minorsite/" local="130267546704205241" remote="130267546700000000" Dst="2" />
<file name="functions.js" server="D:/documents/Dropbox/School/jaar4/Minor/minorsite/" local="130266968731879149" remote="130266968730000000" Dst="2" />
</dwsync>